setup.py
Ranger/__init__.py
Ranger/release.py
Ranger/version.py
Ranger/src/__init__.py
Ranger/src/Collections/RangeBucketMap.py
Ranger/src/Collections/RangeMap.py
Ranger/src/Collections/RangeSet.py
Ranger/src/Collections/__init__.py
Ranger/src/Range/Cut.py
Ranger/src/Range/Range.py
Ranger/src/Range/__init__.py
Ranger/test/__init__.py
Ranger/test/src/__init__.py
Ranger/test/src/mainTestSuite.py
Ranger/test/src/Collections/CollectionsTestSuite.py
Ranger/test/src/Collections/RangeBucketMapTest.py
Ranger/test/src/Collections/RangeMapTest.py
Ranger/test/src/Collections/RangeSetTest.py
Ranger/test/src/Collections/__init__.py
Ranger/test/src/Range/CutTest.py
Ranger/test/src/Range/RangeTest.py
Ranger/test/src/Range/RangeTestSuite.py
Ranger/test/src/Range/__init__.py
ranger.egg-info/PKG-INFO
ranger.egg-info/SOURCES.txt
ranger.egg-info/dependency_links.txt
ranger.egg-info/top_level.txt